{
  "podcast": "omni",
  "summaries": [
    {
      "date": "2026-01-25",
      "datetime": "2026-01-25T01:30:44.215726",
      "content": "# Omni View — Omni‑View Briefing\n**Date:** January 25, 2026\n\n## Top stories (5)\n### 1) US Winter Storm Causes Widespread Disruptions\n**What happened (neutral):** A major winter storm has affected much of the US, leading to over 14,500 flight cancellations, halted train services, and power outages for thousands. It also triggered a grid emergency and is expected to bring up to a foot of snow to New York City and the Northeast on Sunday. Details on the full extent of impacts remain based on initial reports.\n**Why it matters:** This storm could strain emergency services and infrastructure, affecting daily life for millions in travel, energy, and safety. It highlights ongoing challenges with severe weather preparedness in populated areas.\n**Perspectives (multiple viewpoints):**\n- **Perspective 1:** From a center-leaning view, the storm underscores the need for better national infrastructure to handle extreme weather events amid climate changes.\n- **Perspective 2:** Some might see it as a routine seasonal issue, emphasizing personal preparedness over systemic failures.\n**Questions to consider:**\n- How might this storm impact vulnerable populations, like those without heating?\n- What role could climate patterns play in the storm's severity?\n- How reliable are current forecasts for predicting such events?\n**Read more (sources):**\n- [Bloomberg](https://www.bloomberg.com/news/articles/2026-01-25/winter-storm-shakes-energy-transportation-across-the-us) — Reports on flight cancellations, power outages, and snow threats.\n\n### 2) Minnesota Governor Urges Halt to ICE Operations After Fatal Shooting\n**What happened (neutral):** Governor Tim Walz called on President Trump to stop ICE operations in Minnesota following another fatal shooting involving federal agents. Walz described the officers as violent and untrained, demanding their removal from the state. Specific details about the shooting incident are limited in available reports.\n**Why it matters:** This could escalate tensions between state and federal authorities on immigration enforcement, potentially affecting public safety and policy debates.\n**Perspectives (multiple viewpoints):**\n- **Perspective 1:** From a center-leaning perspective, it highlights concerns over federal overreach and the need for accountability in law enforcement actions.\n- **Perspective 2:** Supporters of ICE might view the operations as necessary for national security, questioning the governor's characterization.\n**Questions to consider:**\n- What evidence supports claims of untrained officers?\n- How might this affect immigration policies in other states?\n- What are the potential risks of continuing or halting such operations?\n**Read more (sources):**\n- [CNBC](https://www.cnbc.com/2026/01/24/walz-trump-ice-shooting.html) — Covers Walz's statements on the shooting and call to end operations.\n\n### 3) ICE Seeks Ad Tech and Big Data Tools for Investigations\n**What happened (neutral):** ICE has inquired about commercial ad tech and big data tools for potential use in law enforcement and surveillance activities. A federal filing shows the agency is exploring these technologies. The exact tools or implementation plans are not detailed in the available information.\n**Why it matters:** This could expand government surveillance capabilities, raising questions about privacy and the role of private tech in public investigations.\n**Perspectives (multiple viewpoints):**\n- **Perspective 1:** From a tech/science viewpoint, it demonstrates how commercial tools are increasingly integrated into government operations for efficiency.\n- **Perspective 2:** Critics might argue it risks overreach into personal data without sufficient oversight.\n**Questions to consider:**\n- What privacy protections exist for such tools?\n- How might this affect public trust in government agencies?\n- What alternatives to big data could be used for investigations?\n**Read more (sources):**\n- [Wired](https://www.wired.com/story/ice-asks-companies-about-ad-tech-and-big-data-tools/) — Discusses ICE's filing on commercial tools for surveillance.\n\n### 4) Smear Campaign Targets Victim of Border Patrol Shooting\n**What happened (neutral):** Following a shooting by a federal immigration officer in Minneapolis, the Trump administration and right-wing influencers quickly disparaged the victim, Alex Pretti. The campaign began minutes after the incident. Details on the shooting itself are not fully clear from the report.\n**Why it matters:** It illustrates how information can spread rapidly online, potentially influencing public opinion and investigations into such events.\n**Perspectives (multiple viewpoints):**\n- **Perspective 1:** From a tech/science lens, this shows the speed of digital misinformation in politicized incidents.\n- **Perspective 2:** Supporters might see the responses as highlighting relevant background on the victim.\n**Questions to consider:**\n- How can people verify claims made in online campaigns?\n- What impact does this have on the victim's family and community?\n- Why do such campaigns emerge so quickly after incidents?\n**Read more (sources):**\n- [Wired](https://www.wired.com/story/the-instant-smear-campaign-against-border-patrol-shooting-victim-alex-pretti/) — Covers the rapid disparagement by administration and influencers.\n\n### 5) No Detention or Bail Needed for Women Charged in Church Disruption\n**What happened (neutral):** Two women charged with conspiracy for disrupting a church service in St. Paul were not required to have a detention hearing or bail, per a federal judge's decision. The case involves a criminal complaint. Further details on the disruption are limited.\n**Why it matters:** This ruling could set precedents for handling similar protest-related charges, affecting free speech and assembly rights.\n**Perspectives (multiple viewpoints):**\n- **Perspective 1:** An independent view might emphasize the balance between protest rights and maintaining order in public spaces.\n- **Perspective 2:** Critics could argue it downplays the seriousness of disrupting religious services.\n**Questions to consider:**\n- What factors influenced the judge's decision?\n- How does this compare to similar cases elsewhere?\n- What are the boundaries of protected protest activities?\n**Read more (sources):**\n- [Reason](https://reason.com/volokh/2026/01/24/no-detention-hearing-or-bail-required-for-two-women-charged-with-disrupting-st-paul-church-service/) — Details the judge's ruling on detention and bail.\n\n## Top world stories (5)\n### 1) Russian Attacks on Ukraine Cause Power Outages and Casualties\n**What happened (neutral):** Russian strikes on Ukraine's energy infrastructure killed at least one person and left about 1.2 million properties without power, including explosions in Kyiv. Nearly 6,000 buildings in the capital lost heating amid freezing temperatures. The scale of the assault is based on early reports.\n**Why it matters:** These attacks could worsen humanitarian conditions in Ukraine, straining international aid and escalating the ongoing conflict.\n**Perspectives (multiple viewpoints):**\n- **Perspective 1:** An international perspective highlights the targeting of civilian infrastructure as a potential war crime.\n- **Perspective 2:** Some might view it as a strategic military move in the broader conflict.\n**Questions to consider:**\n- How will this affect Ukraine's winter resilience?\n- What international responses might follow?\n- How accurate are reports of civilian impacts?\n**Read more (sources):**\n- [France 24](https://www.france24.com/en/russian-strikes-kill-one-leave-millions-without-power) — Reports on casualties, power cuts, and heating losses.\n\n### 2) Canadian PM to Speak in Australia Amid Domestic Investigations\n**What happened (neutral):** Canadian Prime Minister Mark Carney is set to address the Australian parliament, while Australian police investigate an unconfirmed sighting of a murder suspect from Lake Cargelligo. Smoke from a bushfire in Victoria is also noted. Details on the speech or investigation outcomes are unclear.\n**Why it matters:** This could influence bilateral relations and highlight ongoing security and environmental issues in Australia.\n**Perspectives (multiple viewpoints):**\n- **Perspective 1:** A center/left view might focus on international diplomacy amid local crises like fires and manhunts.\n- **Perspective 2:** Others could see it as routine political engagement unrelated to domestic events.\n**Questions to consider:**\n- What topics might Carney address?\n- How reliable is the suspect sighting?\n- What are the risks from the ongoing bushfire?\n**Read more (sources):**\n- [The Guardian](https://www.theguardian.com/australia-news/live/2026/jan/25/victoria-otways-bushfires-nsw-lake-cargelligo-manhunt-federal-politics-anthony-albanese-labor-sussan-ley-coalition-ntwnfb) — Covers Carney's address and police investigation.\n\n## Top business stories (3)\n### 1) Protests Erupt Across US After Fatal Shooting by Federal Agents\n**What happened (neutral):** Large protests occurred in cities like Minneapolis, New York, Boston, and Providence following the fatal shooting of 37-year-old nurse Alex Pretti by ICE agents. The demonstrations built on marches the previous day. Specific protest sizes and outcomes are not detailed.\n**Why it matters:** These events could impact public discourse on immigration enforcement and lead to policy changes or further unrest.\n**Perspectives (multiple viewpoints):**\n- **Perspective 1:** A center/left perspective emphasizes community outrage over perceived excessive force.\n- **Perspective 2:** Some might argue the protests disrupt order while investigations proceed.\n**Questions to consider:**\n- What demands are protesters making?\n- How might this affect federal operations?\n- Are there risks of escalation in protests?\n**Read more (sources):**\n- [The Guardian](https://www.theguardian.com/us-news/2026/jan/24/protests-alex-pretti-killing-federal-agents-ice) — Describes protests in multiple cities after the shooting.\n\n### 2) Trump Warns of Tariffs on Canada Over China Trade Talks\n**What happened (neutral):** President Trump threatened 100% tariffs on all Canadian exports if Canada proceeds with a trade deal with China. This follows strained relations between the US and Canada. Details on the potential deal are limited.\n**Why it matters:** Such tariffs could disrupt North American trade, affecting economies and global supply chains.\n**Perspectives (multiple viewpoints):**\n- **Perspective 1:** An international view sees this as escalating trade tensions with broader economic ripple effects.\n- **Perspective 2:** Supporters might view it as protecting US interests against foreign deals.\n**Questions to consider:**\n- What would be the economic impact of these tariffs?\n- How likely is Canada to pursue the China deal?\n- What diplomatic options exist to resolve this?\n**Read more (sources):**\n- [France 24](https://www.france24.com/en/americas/20260124-trump-threatens-100-tariffs-on-canadian-goods-over-pending-china-trade-deal) — Covers Trump's tariff threats and relations strain.\n\n### 3) Weight-Loss Drugs Influence Consumer Spending Patterns\n**What happened (neutral):** The rising popularity of GLP-1 weight-loss drugs is changing how people spend, with businesses adapting to new consumer behaviors. Specific examples of changes are not detailed in the report. It's unclear how widespread these shifts are.\n**Why it matters:** This could reshape industries like food, fashion, and healthcare, reflecting health trends in the economy.\n**Perspectives (multiple viewpoints):**\n- **Perspective 1:** A center/left perspective notes potential benefits for public health but questions accessibility.\n- **Perspective 2:** Businesses might see opportunities in adapting products to new habits.\n**Questions to consider:**\n- What specific spending changes are occurring?\n- How sustainable are these drug-driven trends?\n- What health risks should users consider?\n**Read more (sources):**\n- [BBC](https://www.bbc.com/news/articles/cj6wy85l3x5o?at_medium=RSS&at_campaign=rss) — Explores business adaptations to weight-loss drug users.\n\n## Top technology stories (3)\n### 1) UK Politician Warns Against Left-Wing Election Gains\n**What happened (neutral):** British Conservative MP Brendan Clarke-Smith argued for a strong majority for Kemi Badenoch and the Conservatives in the next election to avoid left-wing policies. He described it as preventing a \"nightmare\" scenario. Details on election timing or polls are not provided.\n**Why it matters:** This reflects ongoing political debates in the UK that could influence voter turnout and party strategies.\n**Perspectives (multiple viewpoints):**\n- **Perspective 1:** A center/right view supports the call for conservative unity to maintain power.\n- **Perspective 2:** Opponents might see it as fearmongering against legitimate political alternatives.\n**Questions to consider:**\n- What policies are at stake in the election?\n- How divided is the Conservative Party?\n- What do current polls indicate?\n**Read more (sources):**\n- [Daily Mail](https://www.dailymail.co.uk/debate/article-15495625/BRENDAN-CLARKE-SMITH-Lets-not-sleepwalk-nightmare-letting-Left-again.html?ns_mchannel=rss&ito=1490&ns_campaign=1490) — Features Clarke-Smith's opinion on election outcomes.\n\n### 2) Senate Democrats Oppose DHS Funding Amid Shooting Fallout\n**What happened (neutral):** Senate Democrats are rejecting a DHS funding bill following the fatal shooting of Alex Pretti by a border patrol agent in Minneapolis, increasing shutdown risks ahead of a Friday deadline. This breaks a prior truce. Funding details are limited.\n**Why it matters:** A potential government shutdown could halt services, amplifying debates on immigration and federal funding.\n**Perspectives (multiple viewpoints):**\n- **Perspective 1:** A center/right perspective blames Democrats for politicizing funding during chaos.\n- **Perspective 2:** Supporters of the revolt might prioritize accountability over budget continuity.\n**Questions to consider:**\n- What are the key disputes in the funding bill?\n- How would a shutdown affect daily operations?\n- Can a compromise be reached before the deadline?\n**Read more (sources):**\n- [Fox News](https://www.foxnews.com/politics/senate-dems-revolt-against-dhs-funding-bill-amid-minneapolis-chaos-dramatically-hiking-government-shutdown-ri) — Reports on Democratic opposition and shutdown risks.\n\n### 3) Fashion Trends in Reality Show 'The Traitors' Analyzed\n**What happened (neutral):** The BBC show 'The Traitors' features distinctive fashion like knitwear and jumpsuits that influence contestant interactions, drawing comparisons to games like Cluedo. It's unclear how this affects viewership. The analysis focuses on style's role in the program.\n**Why it matters:** This highlights how media entertainment blends fashion and psychology, potentially influencing trends.\n**Perspectives (multiple viewpoints):**\n- **Perspective 1:** A center/left view sees it as creative expression enhancing the show's appeal.\n- **Perspective 2:** Critics might dismiss it as superficial amid deeper game strategies.\n**Questions to consider:**\n- How does fashion impact social dynamics in the show?\n- What broader cultural trends does this reflect?\n- Is this unique to 'The Traitors' or common in reality TV?\n**Read more (sources):**\n- [BBC](https://www.bbc.com/news/articles/ce9y1747z3go?at_medium=RSS&at_campaign=rss) — Explains fashion elements in the show.\n\n## Top popular media stories (3)\n### 1) Climber Attempts Rope-Free Ascent of Taiwan Skyscraper\n**What happened (neutral):** Daredevil Alex Honnold began a free solo climb of the 1,667-foot Taipei 101 tower in Taiwan, broadcast live on Netflix. It was formerly the world's tallest building. Safety details or outcomes are not",
      "episode_num": 2,
      "episode_title": "Omni View — Omni‑View Briefing — January 25, 2026",
      "audio_url": "https://raw.githubusercontent.com/patricknovak/Tesla-shorts-time/main/digests/Omni_View_Ep002_20260125.mp3",
      "rss_url": "https://raw.githubusercontent.com/patricknovak/Tesla-shorts-time/main/omni_view_podcast.rss"
    },
    {
      "date": "2026-01-23",
      "datetime": "2026-01-23T19:52:46.783214",
      "content": "📰⚖️ **Omni View - Balanced News Digest**\n\n📅 **Date:** January 23, 2026\n\n🔍 **Balanced Perspectives on Today's News**\n\n**1. Panic buying grips America as historic winter storm closes in... and millions could be left without heat for DAYS: Live updates**\n📺 *Daily Mail*\n\n**2. Katie Price's ex JJ Slater is 'blindsided' by her engagement to mystery man weeks after they split and has flown to Miami with family to 'heal his broken heart'**\n📺 *Daily Mail*\n\n**3. Sen. Warren blasts CFPB director for undermining Trump's credit card affordability push**\n📺 *CNBC*\n\n**4. Rights advocates welcome Canada’s exclusion from Trump’s ‘Board of Peace’**\n📺 *Al Jazeera*\n\n**5. Air Force One glitch revives replacement push as White House says it 'proves Trump was right again'**\n📺 *Fox News*\n\n**6. Federal judge questions Trump authority on White House ballroom project**\n📺 *Fox News*\n\n**7. 'Framework of a Future Deal' on Greenland Is a Relief**\n📺 *Real Clear Politics*\n\n**8. Will the AI bubble burst or boom?**\n📺 *Al Jazeera*\n\n**9. At Davos, U.S. allies question a fraying world order**\n📺 *NPR*\n\n**10. America’s Reading Crisis That No One Wants to Talk About**\n📺 *Mother Jones*\n\n\n🎙️ **Omni View Daily Podcast Link:** https://podcasts.apple.com/us/podcast/omni-view/idXXXXXXXXXX\n\n#OmniView #BalancedNews #MediaLiteracy",
      "episode_num": 1
    }
  ]
}